python_packaging_distribution/__init__.py
python_packaging_distribution/app.py
python_packaging_distribution/cli.py
python_packaging_distribution/python_packaging_distribution.py
python_packaging_distribution-0.1.0.dist-info/AUTHORS.rst
python_packaging_distribution-0.1.0.dist-info/LICENSE
python_packaging_distribution-0.1.0.dist-info/METADATA
python_packaging_distribution-0.1.0.dist-info/WHEEL
python_packaging_distribution-0.1.0.dist-info/entry_points.txt
python_packaging_distribution-0.1.0.dist-info/top_level.txt
python_packaging_distribution-0.1.0.dist-info/RECORD
