Metadata-Version: 2.1
Name: python-packaging-distribution
Version: 0.1.0
Summary: Basic Python Project for packaging and distribution
Home-page: https://github.com/premvikash/python_packaging_distribution
Author: Prem Vikash Upadhyay
Author-email: premvikashu@gmail.com
License: GNU General Public License v3
Keywords: python_packaging_distribution
Platform: UNKNOWN
Classifier: Development Status :: 2 - Pre-Alpha
Classifier: Intended Audience :: Developers
Classifier: License :: OSI Approved :: GNU General Public License v3 (GPLv3)
Classifier: Natural Language :: English
Classifier: Programming Language :: Python :: 2
Classifier: Programming Language :: Python :: 2.7
Classifier: Programming Language :: Python :: 3
Classifier: Programming Language :: Python :: 3.4
Classifier: Programming Language :: Python :: 3.5
Classifier: Programming Language :: Python :: 3.6
Classifier: Programming Language :: Python :: 3.7
Requires-Dist: Click (>=6.0)
